comet_mpm/__init__.py
comet_mpm/_logging.py
comet_mpm/_version.py
comet_mpm/batch_utils.py
comet_mpm/cli.py
comet_mpm/comet_mpm.py
comet_mpm/config.py
comet_mpm/connection.py
comet_mpm/connection_helpers.py
comet_mpm/constants.py
comet_mpm/data_series.py
comet_mpm/dataset_upload_helpers.py
comet_mpm/environment.py
comet_mpm/exceptions.py
comet_mpm/logging_messages.py
comet_mpm/optional_update.py
comet_mpm/server_address.py
comet_mpm/settings.py
comet_mpm/settings_helper.py
comet_mpm/utils.py
comet_mpm/_json/__init__.py
comet_mpm/_json/numpy_encoder.py
comet_mpm/api_key/__init__.py
comet_mpm/api_key/base64_helper.py
comet_mpm/api_key/comet_api_key.py
comet_mpm/api_objects/__init__.py
comet_mpm/api_objects/api.py
comet_mpm/api_objects/prefix_helpers.py
comet_mpm/api_objects/rest_client.py
comet_mpm/api_objects/model/__init__.py
comet_mpm/api_objects/model/dataframe_converters.py
comet_mpm/api_objects/model/model.py
comet_mpm/authhook/__init__.py
comet_mpm/authhook/aws_sagemaker.py
comet_mpm/aws_lambda/__init__.py
comet_mpm/aws_lambda/lambda_helpers.py
comet_mpm/events/__init__.py
comet_mpm/events/base_event.py
comet_mpm/events/events_from_dataframe.py
comet_mpm/events/label_event.py
comet_mpm/events/prediction_event.py
comet_mpm/sender/__init__.py
comet_mpm/sender/asyncio_sender.py
comet_mpm/sender/base.py
comet_mpm/sender/thread_sender.py
comet_mpm-1.4.4.dist-info/licenses/LICENSE
comet_mpm-1.4.4.dist-info/METADATA
comet_mpm-1.4.4.dist-info/WHEEL
comet_mpm-1.4.4.dist-info/top_level.txt
comet_mpm-1.4.4.dist-info/RECORD
